django_remdow/__init__.py
django_remdow/templatetags/__init__.py
django_remdow/templatetags/remdow.py
django_remdow-0.0.9.dist-info/LICENSE
django_remdow-0.0.9.dist-info/METADATA
django_remdow-0.0.9.dist-info/WHEEL
django_remdow-0.0.9.dist-info/top_level.txt
django_remdow-0.0.9.dist-info/RECORD
